django_models_logging-2.4.dist-info/licenses/LICENSE
models_logging/__init__.py
models_logging/admin.py
models_logging/apps.py
models_logging/helpers.py
models_logging/middleware.py
models_logging/models.py
models_logging/settings.py
models_logging/setup.py
models_logging/signals.py
models_logging/utils.py
models_logging/management/commands/__init__.py
models_logging/management/commands/delete_changes.py
models_logging/migrations/0001_initial.py
models_logging/migrations/0002_auto_20161012_2025.py
models_logging/migrations/0003_auto_20170726_1552.py
models_logging/migrations/0004_auto_20171124_1445.py
models_logging/migrations/0005_auto_20200804_1305.py
models_logging/migrations/0006_auto_20211020_2036.py
models_logging/migrations/0007_migrate_old_fields.py
models_logging/migrations/0008_change_extras.py
models_logging/migrations/0009_alter_change_index_together.py
models_logging/migrations/__init__.py
models_logging/templates/models_logging/change_form.html
models_logging/templates/models_logging/object_history.html
models_logging/templates/models_logging/revert_changes_confirmation.html
models_logging/templates/models_logging/revert_revision_confirmation.html
django_models_logging-2.4.dist-info/METADATA
django_models_logging-2.4.dist-info/WHEEL
django_models_logging-2.4.dist-info/top_level.txt
django_models_logging-2.4.dist-info/RECORD
